mieshah/__init__.py
mieshah/pymieshah.py
mieshah-0.0.1.dist-info/licenses/license.txt
mieshah-0.0.1.dist-info/METADATA
mieshah-0.0.1.dist-info/WHEEL
mieshah-0.0.1.dist-info/top_level.txt
mieshah-0.0.1.dist-info/RECORD
