Metadata-Version: 2.4
Name: mieshah
Version: 0.0.1
Summary:  A Python package to calculate light scattering properties/parameters of spherical particles by using Mie theory.
Home-page: https://github.com/DwaipayanDeb/mieshah
Author: Dwaipayan Deb
Author-email: dwaipayandeb@yahoo.co.in
Classifier: Programming Language :: Python :: 3
Classifier: License :: OSI Approved :: MIT License
Classifier: Operating System :: OS Independent
Requires-Python: >=3.6
License-File: license.txt
Requires-Dist: numpy
Requires-Dist: sympy
Requires-Dist: dimpy
Dynamic: author
Dynamic: author-email
Dynamic: classifier
Dynamic: description
Dynamic: description-content-type
Dynamic: home-page
Dynamic: license-file
Dynamic: requires-dist
Dynamic: requires-python
Dynamic: summary
